README.md
setup.py
Glem.egg-info/PKG-INFO
Glem.egg-info/SOURCES.txt
Glem.egg-info/dependency_links.txt
Glem.egg-info/entry_points.txt
Glem.egg-info/not-zip-safe
Glem.egg-info/requires.txt
Glem.egg-info/top_level.txt
glem/__init__.py
glem/extra-wlt.txt
glem/glem.py
glem/list_proiel_perseus_merged_word_lemma_POS_nofreq
glem/list_proiel_word_lemma_POS_freq
glem/pretrained_models/herodotus/e-mail.rule
glem/pretrained_models/herodotus/frog.cfg.template
glem/pretrained_models/herodotus/froggen.tree
glem/pretrained_models/herodotus/froggen.tree.wgt
glem/pretrained_models/herodotus/hdt_Books_forFrog.10plaatsig.zu.col
glem/pretrained_models/herodotus/hdt_Books_forFrog.10plaatsig.zu.col.data.1paxes
glem/pretrained_models/herodotus/hdt_Books_forFrog.10plaatsig.zu.col.data.known.dddwfWawa
glem/pretrained_models/herodotus/hdt_Books_forFrog.10plaatsig.zu.col.data.known.dddwfWawa.wgt
glem/pretrained_models/herodotus/hdt_Books_forFrog.10plaatsig.zu.col.data.lex
glem/pretrained_models/herodotus/hdt_Books_forFrog.10plaatsig.zu.col.data.lex.ambi.05
glem/pretrained_models/herodotus/hdt_Books_forFrog.10plaatsig.zu.col.data.top500
glem/pretrained_models/herodotus/hdt_Books_forFrog.10plaatsig.zu.col.data.unknown.chnppdddwFawasss
glem/pretrained_models/herodotus/hdt_Books_forFrog.10plaatsig.zu.col.settings
glem/pretrained_models/herodotus/smiley.rule
glem/pretrained_models/herodotus/tokconfig-generic
glem/pretrained_models/herodotus/url.rule
webglem/__init__.py
webglem/webglem.config.yml
webglem/webglem.py
webglem/webglem.wsgi
webglem/webglem_wrapper.py