Metadata-Version: 2.1
Name: Glem
Version: 1.3.1
Summary: GLEM is a lemmatizer for Ancient Greek.
Home-page: https://github.com/GreekPerspective/glem
Author: Corien Bary, Iris Hendrickx, Peter Berck, Wessel Stoop
Author-email: c.bary@let.ru.nl
License: GPL-3.0-only
Keywords: nlp computational_linguistics entities linguistics ancient_greek,lemmatizer lemmatization frog clam webservice rest
Classifier: Development Status :: 4 - Beta
Classifier: Topic :: Internet :: WWW/HTTP :: WSGI :: Application
Classifier: Topic :: Text Processing :: Linguistic
Classifier: Programming Language :: Python :: 3
Classifier: Operating System :: POSIX
Classifier: Intended Audience :: Developers
Classifier: Intended Audience :: Science/Research
Classifier: License :: OSI Approved :: GNU General Public License v3 (GPLv3)
